qualesim-1.0.2.dist-info/LICENSE
qualesim-1.0.2.dist-info/top_level.txt
qualesim-1.0.2.dist-info/WHEEL
qualesim-1.0.2.dist-info/RECORD
qualesim-1.0.2.dist-info/METADATA
qualesim.libs/libdqcsim-4b836899.so
qualesim-1.0.2.data/data/lib/libdqcsim.so
qualesim-1.0.2.data/data/lib/cmake/dqcsim/dqcsimConfig.cmake
qualesim-1.0.2.data/data/lib/cmake/dqcsim/dqcsimConfigVersion.cmake
qualesim-1.0.2.data/data/bin/dqcsbepy
qualesim-1.0.2.data/data/bin/dqcsopnull
qualesim-1.0.2.data/data/bin/dqcsfepy
qualesim-1.0.2.data/data/bin/dqcsfenull
qualesim-1.0.2.data/data/bin/dqcsoppy
qualesim-1.0.2.data/data/bin/dqcsbenull
qualesim-1.0.2.data/data/bin/dqcsim
qualesim-1.0.2.data/data/include/cdqcsim
qualesim-1.0.2.data/data/include/dqcsim.h
qualesim-1.0.2.data/data/include/dqcsim
qualesim-1.0.2.data/data/lib64/libdqcsim.so
qualesim/__init__.py
qualesim/common/cq.py
qualesim/common/__init__.py
qualesim/common/cmd.py
qualesim/common/arb.py
qualesim/common/meas.py
qualesim/common/handle.py
qualesim/common/mset.py
qualesim/common/qbset.py
qualesim/plugin/__init__.py
qualesim/host/__init__.py
dqcsim/_dqcsim.cpython-39-x86_64-linux-gnu.so
