Metadata-Version: 2.1
Name: qualesim
Version: 1.0.2
Summary: Quingo Simulator Backend QuaLeSim
Home-page: https://gitee.com/quingo/qualesim.git
Author: Dingdong Liu
Author-email: dingdongliu@quanta.org.cn
License: Apache-2.0
Project-URL: Bug Tracker, https://gitee.com/quingo/qualesim.git
Project-URL: Documentation, https://gitee.com/quingo/qualesim.git
Project-URL: Source Code, https://gitee.com/quingo/qualesim.git
Platform: linux
Classifier: License :: OSI Approved :: Apache Software License
Classifier: Operating System :: POSIX :: Linux
Classifier: Operating System :: MacOS
Classifier: Programming Language :: C
Classifier: Programming Language :: C++
Classifier: Programming Language :: Rust
Classifier: Programming Language :: Python :: 3 :: Only
Classifier: Topic :: Scientific/Engineering
License-File: LICENSE
Requires-Dist: cbor
Requires-Dist: qualesim-quiets (>=1.0.8)
Requires-Dist: qualesim-quantumsim (>=1.0.3)
Requires-Dist: qualesim-qcis (>=1.0.1)
Provides-Extra: tequila
Requires-Dist: qualesim-tequila (>=1.0.0) ; extra == 'tequila'
